pwx_db/__init__.py
pwx_db/db/__init__.py
pwx_db/db/postgres/__init__.py
pwx_db/db/postgres/native_sqls.py
pwx_db/db/postgres/pwx_postegres.py
pwx_db/db/redis/__init__.py
pwx_db/db/redis/pwx_redis.py
pwx_db/db/redis/pwx_redis_service.py
pwx_db/enums/__init__.py
pwx_db/services/__init__.py
pwx_db/services/base_service.py
pwx_db/sync/__init__.py
pwx_db/sync/entity_sync.py
pwx_db/sync/orm_sync.py
pwx_db/sync/persist_sync.py
pwx_db_connection-1.5.3.dist-info/METADATA
pwx_db_connection-1.5.3.dist-info/WHEEL
pwx_db_connection-1.5.3.dist-info/top_level.txt
pwx_db_connection-1.5.3.dist-info/RECORD
