Metadata-Version: 2.1
Name: pwx-db-connection
Version: 1.5.3
Summary: Connection to PostgreSQL and Redis - PWX
Home-page: UNKNOWN
Author: Guilherme Rosa Koerich
Author-email: guilherme@pwx.cloud
License: UNKNOWN
Keywords: connection redis postgres pwx
Platform: UNKNOWN
Classifier: Programming Language :: Python :: 3
Classifier: Programming Language :: Python :: 3.7
Requires-Python: >3.4
Requires-Dist: redis (==3.3.11)
Requires-Dist: psycopg2-binary (==2.8.4)
